[
{"First Name": "First", "Last Name": "Last", "ID": "38798", "Gender (required)": "M", "Grade (required)": "6", "Age (required)": "10", "Height - Feet": "4", "Height - Inches": "10", "Weight - Pounds": "100", "BMI": "22", "Triceps Skinfold": "Test", "Calf Skinfold": "Test", "Percent Body Fat-Calculated": "Test", "Percent Body Fat-Entered": "Test", "20M PACER Laps": "Test", "15M PACER Laps": "Test", "PACER VO2max": "Test", "Mile Run - Minutes": "Test", "Mile Run - Seconds": "Test", "Mile Run VO2max": "Test", "Walk Test - Minutes": "Test", "Walk Test - Seconds": "Test", "Walk Test - HR (BPM)": "Test", "Walk Test VO2max": "Test", "Curl-up (Number)": "Test", "Trunk Lift (Inches)": "Test", "Push-up (Number)": "Test", "Mod Pull-up (Number)": "Test", "Flexed Arm Hang (Seconds)": "Test", "Sit & Reach L (Inches)": "Test", "Sit & Reach R (Inches)": "Test", "Shoulder Stretch L": "Test", "Shoulder Stretch R" : "Test"},
{"First Name": "Test", "Last Name": "Number2", "ID": "38799", "Gender (required)": "M", "Grade (required)": "6", "Age (required)": "10", "Height - Feet": "4", "Height - Inches": "10", "Weight - Pounds": "100", "BMI": "22", "Triceps Skinfold": "Test", "Calf Skinfold": "Test", "Percent Body Fat-Calculated": "Test", "Percent Body Fat-Entered": "Test", "20M PACER Laps": "Test", "15M PACER Laps": "Test", "PACER VO2max": "Test", "Mile Run - Minutes": "Test", "Mile Run - Seconds": "Test", "Mile Run VO2max": "Test", "Walk Test - Minutes": "Test", "Walk Test - Seconds": "Test", "Walk Test - HR (BPM)": "Test", "Walk Test VO2max": "Test", "Curl-up (Number)": "Test", "Trunk Lift (Inches)": "Test", "Push-up (Number)": "Test", "Mod Pull-up (Number)": "Test", "Flexed Arm Hang (Seconds)": "Test", "Sit & Reach L (Inches)": "Test", "Sit & Reach R (Inches)": "Test", "Shoulder Stretch L": "Test", "Shoulder Stretch R" : "Test"}
]